ttgtcanvas/__init__.py
ttgtcanvas/_version.py
ttgtcanvas/labextension/package.json
ttgtcanvas/labextension/static/185.d8efbcab4105e3b3184e.js
ttgtcanvas/labextension/static/261.13b367ad1a25ae40e442.js
ttgtcanvas/labextension/static/261.acb271c86428137219b4.js
ttgtcanvas/labextension/static/480.7ab8b7c9db291d334dbc.js
ttgtcanvas/labextension/static/486.63a8019af6f10cd79d33.js
ttgtcanvas/labextension/static/486.63a8019af6f10cd79d33.js.LICENSE.txt
ttgtcanvas/labextension/static/568.0108a41323911bc33c9c.js
ttgtcanvas/labextension/static/568.5e391d7017567b27c465.js
ttgtcanvas/labextension/static/remoteEntry.2d20435daa740ccce897.js
ttgtcanvas/labextension/static/remoteEntry.85539b2bdb295254dff5.js
ttgtcanvas/labextension/static/style.js
ttgtcanvas/modules/__init__.py
ttgtcanvas/modules/maze.py
ttgtcanvas/nbextension/extension.js
ttgtcanvas/nbextension/index.js
ttgtcanvas/nbextension/index.js.LICENSE.txt
ttgtcanvas-0.3.2.data/data/etc/jupyter/nbconfig/notebook.d/ttgtcanvas.json
ttgtcanvas-0.3.2.data/data/share/jupyter/labextensions/ttgtcanvas/install.json
ttgtcanvas-0.3.2.data/data/share/jupyter/labextensions/ttgtcanvas/package.json
ttgtcanvas-0.3.2.data/data/share/jupyter/labextensions/ttgtcanvas/static/185.d8efbcab4105e3b3184e.js
ttgtcanvas-0.3.2.data/data/share/jupyter/labextensions/ttgtcanvas/static/261.13b367ad1a25ae40e442.js
ttgtcanvas-0.3.2.data/data/share/jupyter/labextensions/ttgtcanvas/static/480.7ab8b7c9db291d334dbc.js
ttgtcanvas-0.3.2.data/data/share/jupyter/labextensions/ttgtcanvas/static/486.63a8019af6f10cd79d33.js
ttgtcanvas-0.3.2.data/data/share/jupyter/labextensions/ttgtcanvas/static/486.63a8019af6f10cd79d33.js.LICENSE.txt
ttgtcanvas-0.3.2.data/data/share/jupyter/labextensions/ttgtcanvas/static/568.5e391d7017567b27c465.js
ttgtcanvas-0.3.2.data/data/share/jupyter/labextensions/ttgtcanvas/static/remoteEntry.2d20435daa740ccce897.js
ttgtcanvas-0.3.2.data/data/share/jupyter/labextensions/ttgtcanvas/static/style.js
ttgtcanvas-0.3.2.dist-info/METADATA
ttgtcanvas-0.3.2.dist-info/WHEEL
ttgtcanvas-0.3.2.dist-info/top_level.txt
ttgtcanvas-0.3.2.dist-info/RECORD
