Metadata-Version: 2.1
Name: ttgtcanvas
Version: 0.3.2
Summary: A Custom Jupyter Widget Library for canvas
Home-page: https://github.com/indreshvishwakarma/ttgtcanvas
Author: Indresh Vishwakarma
Author-email: indresh@varsito.com
License: UNKNOWN
Keywords: ipython,jupyter,widgets
Platform: UNKNOWN
Classifier: Development Status :: 4 - Beta
Classifier: Framework :: IPython
Classifier: Intended Audience :: Developers
Classifier: Intended Audience :: Science/Research
Classifier: Topic :: Multimedia :: Graphics
Classifier: Programming Language :: Python :: 3.6
Classifier: Programming Language :: Python :: 3.7
Classifier: Programming Language :: Python :: 3.8
Classifier: Programming Language :: Python :: 3.9
Requires-Dist: ipywidgets (>=7.6.0)
